bland/__init__.py
bland/batches/__init__.py
bland/batches/client.py
bland/batches/types/__init__.py
bland/batches/types/analysis_object.py
bland/batches/types/analyze_batch_request.py
bland/batches/types/batch_analysis_object.py
bland/batches/types/batch_call_data.py
bland/batches/types/batch_details_response.py
bland/batches/types/batch_object.py
bland/batches/types/batch_params.py
bland/batches/types/call_data.py
bland/batches/types/call_length.py
bland/batches/types/call_length_summary.py
bland/batches/types/call_params.py
bland/batches/types/list_batches_response.py
bland/batches/types/queue_status.py
bland/batches/types/retrieve_batch_analysis_response.py
bland/batches/types/send_batch_request.py
bland/batches/types/send_batch_response.py
bland/batches/types/status_enum.py
bland/batches/types/stop_active_batch_response.py
bland/calls/__init__.py
bland/calls/client.py
bland/calls/types/__init__.py
bland/calls/types/analyze_call.py
bland/calls/types/analyze_call_response.py
bland/calls/types/answered_by_enum.py
bland/calls/types/audio_recording_response.py
bland/calls/types/call_details_response.py
bland/calls/types/call_id_param.py
bland/calls/types/goal.py
bland/calls/types/list_calls_response.py
bland/calls/types/listed_call_data.py
bland/calls/types/stop_call_response.py
bland/calls/types/transcript.py
bland/calls/types/user_enum.py
bland/client.py
bland/commons/__init__.py
bland/commons/errors/__init__.py
bland/commons/errors/bad_request_error.py
bland/commons/errors/server_error.py
bland/commons/errors/unauthorized_error.py
bland/commons/types/__init__.py
bland/commons/types/call_id.py
bland/commons/types/custom_tool.py
bland/commons/types/error_body.py
bland/commons/types/error_detail.py
bland/commons/types/phone_number.py
bland/commons/types/status.py
bland/commons/types/tools.py
bland/commons/types/voice_id.py
bland/commons/types/webhook.py
bland/core/__init__.py
bland/core/api_error.py
bland/core/client_wrapper.py
bland/core/datetime_utils.py
bland-0.3.0.dist-info/METADATA
bland-0.3.0.dist-info/WHEEL
bland-0.3.0.dist-info/RECORD
